penguindashboard/AntiBERTa2_getLogits.py
penguindashboard/BLAST_phylo.py
penguindashboard/ESM2_getLogits.py
penguindashboard/ProteinMPNN_getLogits.py
penguindashboard/SaProt_getLogits.py
penguindashboard/__init__.py
penguindashboard/edit_mutcompute_output.py
penguindashboard/esm_fold.py
penguindashboard/pipeline.py
penguindashboard/score.py
penguindashboard-1.0.13.dist-info/LICENSE.txt
penguindashboard-1.0.13.dist-info/METADATA
penguindashboard-1.0.13.dist-info/WHEEL
penguindashboard-1.0.13.dist-info/entry_points.txt
penguindashboard-1.0.13.dist-info/top_level.txt
penguindashboard-1.0.13.dist-info/RECORD
