Metadata-Version: 2.1
Name: penguindashboard
Version: 1.0.13
Summary: PEngUIN: Protein Engineering Using Independent Networks
Home-page: https://github.com/AaronFeller/PEngUIN
Author: ['Aaron Feller', 'Phillip Woolley']
Author-email: ['aaronleefeller@gmail.com', 'prwoolley@utexas.edu']
License: MIT
Classifier: Development Status :: 4 - Beta
Classifier: Intended Audience :: Science/Research
Classifier: Topic :: Scientific/Engineering :: Bio-Informatics
Classifier: License :: OSI Approved :: MIT License
Classifier: Programming Language :: Python :: 3
Classifier: Programming Language :: Python :: 3.7
Classifier: Programming Language :: Python :: 3.8
Classifier: Programming Language :: Python :: 3.9
Classifier: Programming Language :: Python :: 3.10
Classifier: Programming Language :: Python :: 3.11
Requires-Python: >=3.7
License-File: LICENSE.txt
